{
  "date": "190626",
  "updated_at": "2026-06-19T08:49:07Z",
  "prices": {
    "BARC.L": {
      "name": "Barclays",
      "price": 497.9,
      "change_pct_1d": -0.54,
      "change_pct_5d": 5.3,
      "change_pct_30d": 13.54,
      "week_52_high": 523.0,
      "week_52_low": 317.85,
      "status": "green"
    },
    "LLOY.L": {
      "name": "Lloyds",
      "price": 104.55,
      "change_pct_1d": -1.41,
      "change_pct_5d": 2.15,
      "change_pct_30d": 6.72,
      "week_52_high": 114.6,
      "week_52_low": 72.851,
      "status": "green"
    },
    "NWG.L": {
      "name": "NatWest",
      "price": 634.8,
      "change_pct_1d": -1.0,
      "change_pct_5d": 3.35,
      "change_pct_30d": 10.93,
      "week_52_high": 705.4,
      "week_52_low": 471.0,
      "status": "green"
    },
    "HSBA.L": {
      "name": "HSBC",
      "price": 1437.2,
      "change_pct_1d": -0.36,
      "change_pct_5d": 4.69,
      "change_pct_30d": 7.63,
      "week_52_high": 1441.2,
      "week_52_low": 860.3,
      "status": "green"
    }
  },
  "sonia": {
    "rate": 3.7303,
    "change_1d": -0.0001,
    "status": "green"
  },
  "alerts": [
    {
      "type": "news_cluster",
      "bank": null,
      "severity": "amber",
      "message": "10 banking-related headlines today"
    }
  ],
  "overall_status": "amber"
}